yeetcode/__init__.py
yeetcode/loader.py
yeetcode/problem.py
yeetcode/struct.py
yeetcode-0.3.0.dist-info/LICENSE
yeetcode-0.3.0.dist-info/METADATA
yeetcode-0.3.0.dist-info/WHEEL
yeetcode-0.3.0.dist-info/entry_points.txt
yeetcode-0.3.0.dist-info/top_level.txt
yeetcode-0.3.0.dist-info/RECORD
