Metadata-Version: 2.1
Name: yeetcode
Version: 0.3.0
Summary: Make your own leetcode problems
Author-email: Qianxy <xyqian67@gmail.com>
Project-URL: Homepage, https://github.com/qianxyz/yeetcode
Project-URL: Bug Tracker, https://github.com/qianxyz/yeetcode/issues
Classifier: Development Status :: 1 - Planning
Classifier: License :: OSI Approved :: MIT License
Classifier: Operating System :: OS Independent
Classifier: Programming Language :: Python :: 3
Requires-Python: >=3.8
License-File: LICENSE
Requires-Dist: PyYAML (~=6.0)
Requires-Dist: black (~=22.10.0)
Provides-Extra: tests
Requires-Dist: flake8 (~=5.0.4) ; extra == 'tests'
Requires-Dist: pytest (~=7.1.3) ; extra == 'tests'
Requires-Dist: coverage[toml] (~=6.5.0) ; extra == 'tests'
